cachedcomplete/__init__.py
cachedcomplete/main_script.py
cachedcomplete/parser_cache.py
cachedcomplete-1.0.4.dist-info/LICENSE
cachedcomplete-1.0.4.dist-info/METADATA
cachedcomplete-1.0.4.dist-info/WHEEL
cachedcomplete-1.0.4.dist-info/top_level.txt
cachedcomplete-1.0.4.dist-info/RECORD
