Metadata-Version: 2.1
Name: cachedcomplete
Version: 1.0.4
Summary: Cached wrapper for python argcomplete
Home-page: https://github.com/Roynecro97/cachedcomplete
Author: 
Author-email: 
License: MIT License
Project-URL: Source Code, https://github.com/Roynecro97/cachedcomplete
Platform: MacOS X
Platform: Posix
Classifier: Environment :: Console
Classifier: Intended Audience :: Developers
Classifier: License :: OSI Approved :: MIT License
Classifier: Operating System :: MacOS :: MacOS X
Classifier: Operating System :: POSIX
Classifier: Programming Language :: Python
Classifier: Programming Language :: Python :: 2
Classifier: Programming Language :: Python :: 2.7
Classifier: Programming Language :: Python :: 3
Classifier: Programming Language :: Python :: 3.5
Classifier: Programming Language :: Python :: 3.6
Classifier: Programming Language :: Python :: 3.7
Classifier: Programming Language :: Python :: 3.8
Classifier: Programming Language :: Python :: Implementation :: CPython
Classifier: Development Status :: 4 - Beta
Classifier: Topic :: Software Development
Classifier: Topic :: Software Development :: Libraries :: Python Modules
Classifier: Topic :: System :: Shells
Classifier: Topic :: Terminals
Requires-Dist: argcomplete (>=1.11.1)
